setup.py
ammo/__init__.py
ammo.egg-info/PKG-INFO
ammo.egg-info/SOURCES.txt
ammo.egg-info/dependency_links.txt
ammo.egg-info/not-zip-safe
ammo.egg-info/top_level.txt
ammo/lunapark/__init__.py
ammo/lunapark/generator.py
ammo/phantom/__init__.py