Metadata-Version: 1.1
Name: ammo
Version: 0.0.7
Summary: Input data generator for different load tools
Home-page: https://github.com/greggyNapalm/ammo
Author: Gregory Komissarov
Author-email: gregory.komissarov@gmail.com
License: BSD
Keywords: phantom,yandex-tank,ammo
Platform: UNKNOWN
Classifier: Development Status :: 4 - Beta
Classifier: Environment :: Console
Classifier: Intended Audience :: Developers
Classifier: License :: OSI Approved :: BSD License
Classifier: Operating System :: OS Independent
Classifier: Programming Language :: Python :: 2
Classifier: Topic :: Software Development :: Libraries :: Python Modules
Classifier: Topic :: Utilities
